dek/__init__.py
dek/py.typed
dek-1.4.2.dist-info/LICENSE
dek-1.4.2.dist-info/METADATA
dek-1.4.2.dist-info/WHEEL
dek-1.4.2.dist-info/RECORD
