Metadata-Version: 2.1
Name: dek
Version: 1.4.2
Summary: 🎴 The decorator-decorator 🎴
Home-page: https://github.com/rec/dek
License: MIT
Author: Tom Ritchford
Author-email: tom@swirly.com
Requires-Python: >=3.8
Classifier: License :: OSI Approved :: MIT License
Classifier: Programming Language :: Python :: 3
Classifier: Programming Language :: Python :: 3.8
Classifier: Programming Language :: Python :: 3.9
Classifier: Programming Language :: Python :: 3.10
Classifier: Programming Language :: Python :: 3.11
Classifier: Programming Language :: Python :: 3.12
Requires-Dist: xmod
Project-URL: Documentation, https://rec.github.io/dek
Project-URL: Repository, https://github.com/rec/dek
